{
 "completions": [
  {
   "created_at": 1611746034,
   "id": 107001,
   "lead_time": 2.87,
   "result": [

   ]
  }
 ],
 "data": {
  "batch": "wa_grace_ver02",
  "box": [
   0.5489440165774923,
   0.6745230046419229,
   0.6788064123879016,
   0.8077696012256262
  ],
  "edition_seq_num": 1,
  "filepath": "wa_grace_ver02\/data\/sn83045604\/00202199409\/1896120601\/0073\/005_0_91.jpg",
  "geographic_coverage": [
   "Washington--King--Seattle"
  ],
  "image": "https:\/\/chroniclingamerica.loc.gov\/iiif\/2\/wa_grace_ver02%2Fdata%2Fsn83045604%2F00202199409%2F1896120601%2F0073.jp2\/pct:54.89,67.46,12.99,13.33\/!500,500\/0\/default.jpg",
  "lccn": "sn83045604",
  "name": "The Seattle post-intelligencer. [volume]",
  "ocr": [
   "Books.",
   "jomm",
   "m\u2022",
   "\u2022",
   "'*\u00bb'",
   "\u25a0",
   "\\",
   "j",
   "\u00a3",
   "il",
   "r",
   "-jj",
   "I",
   "K",
   "'",
   "'B'y",
   "\u2022$",
   "t",
   ",\u00ab\u2022",
   "i",
   "]|",
   "WSr",
   "l",
   "f&",
   ".",
   "i",
   ".;*\u00aeaL",
   "V*.Tp>j",
   "5-",
   "3",
   "\u2022.",
   "*<",
   "*",
   "P\"",
   "H",
   "5-jBKs,",
   "Jn*",
   "-",
   "'",
   "ii:",
   "5\u00ab",
   "-HA",
   "\\i",
   "l-iiiilf",
   "li!",
   "u",
   "f",
   "\u2022\u00bb",
   "ty\u00bb",
   "-|",
   "fc",
   "t",
   "\"\u00ab4",
   "*\u2022\u00bb\u00ab\u25a0",
   "4pl",
   ">'",
   "w-.-sJS",
   "-4niU>\u00abmM*Cs",
   "a",
   "-a*",
   "tr",
   "\u2014\u00abai^",
   "..i.j"
  ],
  "page_seq_num": 73,
  "page_url": "https:\/\/chroniclingamerica.loc.gov\/data\/batches\/wa_grace_ver02\/data\/sn83045604\/00202199409\/1896120601\/0073.jp2",
  "place_of_publication": "Seattle, Wash. Terr. [Wash.]",
  "pub_date": "1896-12-06",
  "publisher": "Post-Intelligencer Pub. Co.",
  "score": 0.9177814722061157,
  "url": "https:\/\/news-navigator.labs.loc.gov\/data\/wa_grace_ver02\/data\/sn83045604\/00202199409\/1896120601\/0073\/005_0_91.jpg"
 },
 "id": 107
}