{
 "completions": [
  {
   "created_at": 1611746094,
   "id": 1146001,
   "lead_time": 4.084,
   "result": [
    {
     "from_name": "choice",
     "id": "2bTuAIyfzA",
     "to_name": "image",
     "type": "choices",
     "value": {
      "choices": [
       "animal"
      ]
     }
    }
   ]
  }
 ],
 "data": {
  "batch": "msar_lapis_ver01",
  "box": [
   0.030501860999344883,
   0.3042006327911094,
   0.44588878187578224,
   0.522039810347778
  ],
  "edition_seq_num": 1,
  "filepath": "msar_lapis_ver01\/data\/sn87065613\/00383345157\/1909112001\/1007\/003_0_96.jpg",
  "geographic_coverage": [
   "Mississippi--Oktibbeha--Starkville"
  ],
  "image": "https:\/\/chroniclingamerica.loc.gov\/iiif\/2\/msar_lapis_ver01%2Fdata%2Fsn87065613%2F00383345157%2F1909112001%2F1007.jp2\/pct:3.05,30.43,41.54,21.79\/!500,500\/0\/default.jpg",
  "lccn": "sn87065613",
  "name": "The Southern farm gazette.",
  "ocr": [

  ],
  "page_seq_num": 1007,
  "page_url": "https:\/\/chroniclingamerica.loc.gov\/data\/batches\/msar_lapis_ver01\/data\/sn87065613\/00383345157\/1909112001\/1007.jp2",
  "place_of_publication": "Starkville, Miss.",
  "pub_date": "1909-11-20",
  "publisher": "Dr. Tait Butler",
  "score": 0.9676872491836548,
  "url": "https:\/\/news-navigator.labs.loc.gov\/data\/msar_lapis_ver01\/data\/sn87065613\/00383345157\/1909112001\/1007\/003_0_96.jpg"
 },
 "id": 1146
}