{
 "completions": [
  {
   "created_at": 1611757154,
   "id": 1198001,
   "lead_time": 6.291,
   "result": [
    {
     "from_name": "choice",
     "id": "tvyCE1ofgl",
     "to_name": "image",
     "type": "choices",
     "value": {
      "choices": [
       "human"
      ]
     }
    }
   ]
  }
 ],
 "data": {
  "batch": "dlc_victor_ver01",
  "box": [
   0.31140715642996275,
   0.08133517655310352,
   0.562280560142841,
   0.4204323050902062
  ],
  "edition_seq_num": 1,
  "filepath": "dlc_victor_ver01\/data\/sn84026749\/100492660\/1910032101\/0530\/005_0_99.jpg",
  "geographic_coverage": [
   "District of Columbia--Washington"
  ],
  "image": "https:\/\/chroniclingamerica.loc.gov\/iiif\/2\/dlc_victor_ver01%2Fdata%2Fsn84026749%2F100492660%2F1910032101%2F0530.jp2\/pct:31.14,8.14,25.09,33.91\/!500,500\/0\/default.jpg",
  "lccn": "sn84026749",
  "name": "The Washington times. [volume]",
  "ocr": [
   "VISCOUNT",
   "ACHESON",
   "ACHESONISCOITNT",
   "ACHESONVISCOUNT",
   "ACHESONV",
   "ISCOITNT",
   "ACHBSON",
   "ACHE",
   "ON",
   "is",
   "to",
   "marry",
   "Mildred",
   "Carter",
   "arter",
   "the",
   "daughter",
   "dau",
   "hter",
   "of",
   "our",
   "ourminister",
   "ourmInister",
   "ou",
   "ouminister",
   "r",
   "VISCOUNT",
   "V",
   "minister",
   "to",
   "Roumania",
   "Mr",
   "Carter",
   "was",
   "stationed",
   "in",
   "London",
   "in",
   "the",
   "dip",
   "diplomatic",
   "cUpomaUc",
   "d",
   "domatlc",
   "p",
   "\u00ac",
   "lomatic",
   "service",
   "for",
   "many",
   "years",
   "Aoheson",
   "Aohe",
   "on",
   "is",
   "eldest",
   "elde",
   "son",
   "I50",
   "of",
   "the",
   "fourth",
   "fourthEarl",
   "tCHlrtkEarl",
   "fourthIar",
   "Earl",
   "1",
   "of",
   "Gosford",
   "and",
   "has",
   "served",
   "serve",
   "d",
   "in",
   "Egypt"
  ],
  "page_seq_num": 530,
  "page_url": "https:\/\/chroniclingamerica.loc.gov\/data\/batches\/dlc_victor_ver01\/data\/sn84026749\/100492660\/1910032101\/0530.jp2",
  "place_of_publication": "Washington [D.C.]",
  "pub_date": "1910-03-21",
  "publisher": "Times Pub. Co.",
  "score": 0.9942103624343872,
  "url": "https:\/\/news-navigator.labs.loc.gov\/data\/dlc_victor_ver01\/data\/sn84026749\/100492660\/1910032101\/0530\/005_0_99.jpg"
 },
 "id": 1198
}