{
 "completions": [
  {
   "created_at": 1611673511,
   "id": 1488001,
   "lead_time": 5.265,
   "result": [
    {
     "from_name": "choice",
     "id": "Cr0XsCM08o",
     "to_name": "image",
     "type": "choices",
     "value": {
      "choices": [
       "human",
       "landscape"
      ]
     }
    }
   ]
  }
 ],
 "data": {
  "batch": "pst_fayette_ver01",
  "box": [
   0.16012936144803477,
   0.20633832366493837,
   0.5501993229958864,
   0.4352968905834442
  ],
  "edition_seq_num": 1,
  "filepath": "pst_fayette_ver01\/data\/sn85038411\/00296028125\/1914082001\/0576\/010_0_98.jpg",
  "geographic_coverage": [
   "Pennsylvania--Dauphin--Harrisburg"
  ],
  "image": "https:\/\/chroniclingamerica.loc.gov\/iiif\/2\/pst_fayette_ver01%2Fdata%2Fsn85038411%2F00296028125%2F1914082001%2F0576.jp2\/pct:16.01,20.64,39.01,22.9\/!500,500\/0\/default.jpg",
  "lccn": "sn85038411",
  "name": "Harrisburg telegraph. [volume]",
  "ocr": [
   "ELIZABETH",
   "VILLE'S",
   "CHAMPION",
   "BASEBALL",
   "TEAM",
   "EUZABETH",
   "VILLE",
   "BASEBALL",
   "TEAM,",
   "CHAMPIONS",
   "OF",
   "UFP",
   "ER",
   "DAUPHIN",
   "COUNTY",
   "Left",
   "to",
   "right\u2014",
   "Top",
   "row:",
   "Schultz,",
   "sub.;",
   "Salada,",
   "p.:",
   "P.",
   "'Stroup,",
   "3b.;",
   "H.",
   "Swab,",
   "lb.;",
   "L.",
   "Bufflngton,",
   "cf.;",
   "J.",
   "Wleeu",
   "B.",
   "Stroup,",
   "2b.;",
   "W.",
   "J.",
   "Daniel,",
   "lb.;",
   "A.",
   "W.",
   "Hoke,",
   "manager.",
   "Front",
   "row:",
   "R.",
   "Bufflngton,",
   "ss.;",
   "S.",
   "Tschopp,",
   "rf.;",
   "G.",
   "c.",
   "This",
   "team",
   "won",
   "13",
   "and",
   "lost",
   "2",
   "games;",
   "scored",
   "122",
   "runs;",
   "hits,",
   "162;",
   "opponents,",
   "runs,",
   "39;",
   "hits,",
   "85;",
   "has"
  ],
  "page_seq_num": 576,
  "page_url": "https:\/\/chroniclingamerica.loc.gov\/data\/batches\/pst_fayette_ver01\/data\/sn85038411\/00296028125\/1914082001\/0576.jp2",
  "place_of_publication": "Harrisburg, Pa.",
  "pub_date": "1914-08-20",
  "publisher": "C.H. Bergner",
  "score": 0.9846203327178955,
  "url": "https:\/\/news-navigator.labs.loc.gov\/data\/pst_fayette_ver01\/data\/sn85038411\/00296028125\/1914082001\/0576\/010_0_98.jpg"
 },
 "id": 1488
}