{
 "completions": [
  {
   "created_at": 1611767567,
   "id": 1771001,
   "lead_time": 1.784,
   "result": [
    {
     "from_name": "choice",
     "id": "a6s6taZv9P",
     "to_name": "image",
     "type": "choices",
     "value": {
      "choices": [
       "human"
      ]
     }
    }
   ]
  }
 ],
 "data": {
  "batch": "okhi_inola_ver02",
  "box": [
   0.18831260387714094,
   0.06655316603811164,
   0.4495519491342398,
   0.4800678052400288
  ],
  "edition_seq_num": 1,
  "filepath": "okhi_inola_ver02\/data\/sn86064187\/00200295286\/1918010901\/1001\/009_0_95.jpg",
  "geographic_coverage": [
   "Oklahoma--Oklahoma--Oklahoma City"
  ],
  "image": "https:\/\/chroniclingamerica.loc.gov\/iiif\/2\/okhi_inola_ver02%2Fdata%2Fsn86064187%2F00200295286%2F1918010901%2F1001.jp2\/pct:18.83,6.66,26.13,41.36\/!500,500\/0\/default.jpg",
  "lccn": "sn86064187",
  "name": "The Oklahoma City times. [volume]",
  "ocr": [
   "With",
   "Luring",
   "Young",
   "Girl",
   "From",
   "Home",
   "'",
   "9",
   "m",
   "TISsb",
   "saw.",
   "m.",
   ".saa",
   "fgf",
   "'1HawT",
   "WtKmr",
   "fl",
   "lEBtgaa!",
   "BY",
   "Hk\"",
   "agggsV",
   "-",
   "'",
   "twl",
   "lauBtssssl",
   "I",
   ",",
   "jbb",
   "aL",
   "'-fM",
   "V",
   "'",
   "'",
   "bw",
   "'",
   "Bi'",
   "w",
   "Ik",
   "Jtk",
   "5Sggwl",
   "Br",
   "-",
   "'",
   "'Vidt?'\"''",
   "mmS\"",
   "B9",
   "\"",
   "\"",
   "'",
   "BBBflBBBH",
   "l",
   "K'f",
   "i",
   "aaK,",
   "'Itfi",
   "B",
   "Y",
   "lh",
   "J",
   "'",
   "ggaV",
   "mm",
   "aBajsVI",
   "gar",
   "BBLkwZrMnfl",
   "1",
   "1",
   "sm",
   "Be",
   "'gaa",
   "IbXtSt",
   "I",
   "ikvvi",
   "IbVsV",
   "'2(H",
   "I",
   "H",
   "LW",
   "kH",
   "gMBBvQg",
   "ggV",
   "i",
   "'",
   "gyT",
   "I",
   "IB'",
   "wr",
   "!?S",
   "B",
   "\":r!",
   "Sjric-1",
   "saml",
   "Laura",
   "Banson,",
   "17",
   "years",
   "old,",
   "who",
   "accused",
   "H.",
   "W.",
   "Petrie,",
   "60.",
   "composer",
   "of",
   "in",
   "the",
   "Deep'",
   "of",
   "luring",
   "her",
   "from",
   "her",
   "home",
   "in",
   "Wheaton,",
   "111.",
   "to",
   "Colorado"
  ],
  "page_seq_num": 1001,
  "page_url": "https:\/\/chroniclingamerica.loc.gov\/data\/batches\/okhi_inola_ver02\/data\/sn86064187\/00200295286\/1918010901\/1001.jp2",
  "place_of_publication": "Oklahoma City, Okla.",
  "pub_date": "1918-01-09",
  "publisher": "Oklahoma City Times Co.",
  "score": 0.9535869359970093,
  "url": "https:\/\/news-navigator.labs.loc.gov\/data\/okhi_inola_ver02\/data\/sn86064187\/00200295286\/1918010901\/1001\/009_0_95.jpg"
 },
 "id": 1771
}