{
 "completions": [
  {
   "created_at": 1611764213,
   "id": 1910001,
   "lead_time": 1.762,
   "result": [
    {
     "from_name": "choice",
     "id": "SkAKkG_CyY",
     "to_name": "image",
     "type": "choices",
     "value": {
      "choices": [
       "human"
      ]
     }
    }
   ]
  }
 ],
 "data": {
  "batch": "okhi_dillpickle_ver01",
  "box": [
   0.4242080467334692,
   0.3384971328438689,
   0.6718164144152383,
   0.6219538142896767
  ],
  "edition_seq_num": 1,
  "filepath": "okhi_dillpickle_ver01\/data\/sn86063952\/00295864369\/1919012001\/0131\/009_0_91.jpg",
  "geographic_coverage": [
   "Oklahoma--Logan--Guthrie"
  ],
  "image": "https:\/\/chroniclingamerica.loc.gov\/iiif\/2\/okhi_dillpickle_ver01%2Fdata%2Fsn86063952%2F00295864369%2F1919012001%2F0131.jp2\/pct:42.42,33.85,24.77,28.35\/!500,500\/0\/default.jpg",
  "lccn": "sn86063952",
  "name": "The Guthrie daily leader. [volume]",
  "ocr": [
   ".",
   "GAEDEKS",
   "FHITZ",
   "?L4KTrn",
   "or",
   "xxv",
   "lcvt",
   "FIGHTIKG",
   "HEL?",
   "FEEcHEN",
   "SAMMIE",
   "S",
   ",",
   ",",
   "-.--",
   "--V",
   ".",
   "..........",
   "-",
   ",,",
   ".",
   "i",
   "v-\"!",
   "t",
   "V",
   ":",
   "Y",
   "-",
   "k",
   "'V.",
   "\"'",
   "J",
   "'",
   ".",
   "'",
   "-",
   "-",
   "-",
   "t",
   "i",
   "''''..\"",
   "i",
   "c",
   ".",
   "'.",
   "j",
   "ivv",
   "'",
   "'",
   "\"",
   "-",
   "'",
   "i",
   "J",
   "r",
   "4",
   ";",
   "-",
   "'",
   "-",
   "N",
   "ir,",
   "?",
   "-i:,'\"",
   ".",
   "-",
   "'",
   "I",
   ",",
   "f",
   "-",
   ".",
   ",",
   "t",
   ".",
   "-",
   ",",
   "4",
   ",",
   ".",
   ".",
   ",",
   "...",
   "v-",
   "-",
   ",",
   "....",
   ",",
   "..",
   "7",
   "\".",
   "f",
   ".",
   "i,\"tf",
   "\"",
   ".",
   "-",
   "'",
   ";",
   "'",
   "'",
   "\"",
   "i",
   "i",
   "-",
   "-",
   "-'",
   "\"",
   "'",
   "'",
   ".",
   "-",
   "t.",
   ".",
   ",",
   ",.,",
   ".",
   "j",
   ",.",
   ".",
   "...",
   ".",
   ".",
   ",-.....-",
   "\".'-.\"-.",
   "-",
   "-",
   "'",
   "\"",
   ".",
   ".",
   "s",
   ",",
   ".",
   "i",
   "-",
   ":",
   ":",
   ".........",
   ";",
   ".",
   "i",
   ".",
   "i",
   ".",
   "-",
   "v",
   ".4",
   "w.",
   ".,JL'JL",
   "i.",
   ".",
   "'tr'",
   "\"i.",
   "4",
   ".",
   ".'.\"",
   "'.",
   ";",
   ".",
   "1",
   "\"",
   "v",
   "'",
   "n",
   "..:",
   "'",
   ";",
   "it-",
   ":",
   "c.",
   "\"",
   "\";",
   "'",
   "...i",
   "'",
   "-",
   ":",
   "M",
   "I",
   ",",
   "\"",
   "'",
   "'",
   "t",
   "!\"",
   "\"",
   "....",
   ".",
   ".",
   ":",
   "i",
   "i-f",
   "i.f",
   "\"f",
   "',',.",
   "t",
   ".",
   "i",
   "v",
   "...",
   "'",
   "'",
   "-",
   "'",
   "'",
   "'",
   "\"",
   "::-",
   ",.",
   "w",
   ".",
   "'",
   "w",
   ".:",
   "4:",
   "i",
   "r",
   "-4",
   "-",
   "?",
   "-",
   ";",
   "\"",
   "\"",
   ":",
   ":",
   "4",
   ";",
   ":.",
   "-.",
   ".",
   "...:;",
   "i",
   "\"i't...",
   ":.'.\"",
   "h",
   ",",
   ".",
   ".",
   ",",
   ".",
   "I",
   "J",
   "-!",
   "\"I",
   "?',:.'",
   "i",
   "l",
   "4",
   "f",
   "\"",
   ".",
   "i",
   "1",
   "I",
   ".1",
   "J."
  ],
  "page_seq_num": 131,
  "page_url": "https:\/\/chroniclingamerica.loc.gov\/data\/batches\/okhi_dillpickle_ver01\/data\/sn86063952\/00295864369\/1919012001\/0131.jp2",
  "place_of_publication": "Guthrie, Okla.",
  "pub_date": "1919-01-20",
  "publisher": "Roy Hoffman",
  "score": 0.9133038520812988,
  "url": "https:\/\/news-navigator.labs.loc.gov\/data\/okhi_dillpickle_ver01\/data\/sn86063952\/00295864369\/1919012001\/0131\/009_0_91.jpg"
 },
 "id": 1910
}