{
 "completions": [
  {
   "created_at": 1611768063,
   "id": 192001,
   "lead_time": 2.751,
   "result": [

   ]
  }
 ],
 "data": {
  "batch": "dlc_lotus_ver01",
  "box": [
   0.024805238452045134,
   0.4712745555932971,
   0.46099750212116536,
   0.8371193927267323
  ],
  "edition_seq_num": 1,
  "filepath": "dlc_lotus_ver01\/data\/sn83030214\/00175039156\/1897101001\/0199\/000_0_97.jpg",
  "geographic_coverage": [
   "New York--New York--New York"
  ],
  "image": "https:\/\/chroniclingamerica.loc.gov\/iiif\/2\/dlc_lotus_ver01%2Fdata%2Fsn83030214%2F00175039156%2F1897101001%2F0199.jp2\/pct:2.48,47.13,43.62,36.59\/!500,500\/0\/default.jpg",
  "lccn": "sn83030214",
  "name": "New-York tribune. [volume]",
  "ocr": [

  ],
  "page_seq_num": 199,
  "page_url": "https:\/\/chroniclingamerica.loc.gov\/data\/batches\/dlc_lotus_ver01\/data\/sn83030214\/00175039156\/1897101001\/0199.jp2",
  "place_of_publication": "New York [N.Y.]",
  "pub_date": "1897-10-10",
  "publisher": "New York Tribune",
  "score": 0.9758099913597107,
  "url": "https:\/\/news-navigator.labs.loc.gov\/data\/dlc_lotus_ver01\/data\/sn83030214\/00175039156\/1897101001\/0199\/000_0_97.jpg"
 },
 "id": 192
}