{
 "completions": [
  {
   "created_at": 1611752004,
   "id": 2001,
   "lead_time": 3.19,
   "result": [
    {
     "from_name": "choice",
     "id": "tC24nKcsDP",
     "to_name": "image",
     "type": "choices",
     "value": {
      "choices": [
       "human-structure"
      ]
     }
    }
   ]
  }
 ],
 "data": {
  "batch": "khi_jennison_ver01",
  "box": [
   0.6952927048141891,
   0.8232186664404393,
   0.9501987216708896,
   0.9468576342821277
  ],
  "edition_seq_num": 1,
  "filepath": "khi_jennison_ver01\/data\/sn82014635\/00280760511\/1895042701\/0195\/010_0_90.jpg",
  "geographic_coverage": [
   "Kansas--Sedgwick--Wichita"
  ],
  "image": "https:\/\/chroniclingamerica.loc.gov\/iiif\/2\/khi_jennison_ver01%2Fdata%2Fsn82014635%2F00280760511%2F1895042701%2F0195.jp2\/pct:69.52,82.33,25.5,12.37\/!500,500\/0\/default.jpg",
  "lccn": "sn82014635",
  "name": "The Wichita daily eagle. [volume]",
  "ocr": [
   "WICHITA",
   "l",
   "BBIHSBPilllilllllllIBB",
   "j:",
   "-",
   "i",
   "r.r",
   "julorrniLaa",
   "aiJrtt",
   "MRS",
   "3L",
   "M.",
   "WOOIK",
   "Of",
   "K,",
   "V:",
   "S33",
   "RjrerrjeW",
   "Tea,,",
   "HOSPITAL",
   "AdmlriM",
   "Jo",
   "cald.",
   "TborwJKb",
   "Ijr",
   "i'jipf4",
   "tor",
   "the",
   "cm",
   "tad",
   "ti'iiM&;",
   "ot",
   "di",
   "ogic&I.",
   "obbsV",
   "r",
   "cI",
   "3d",
   "jrys-",
   "CO",
   "OjOCaJ",
   "C.",
   "7nu,t4",
   "nr",
   "com",
   ":n",
   "t",
   "It",
   "is",
   "'hrj.",
   "UjrtKr",
   "wtuj",
   "as",
   "ftntaMst",
   "rjntfm",
   "ct",
   "Jlyi",
   "r",
   "io",
   "ad",
   "maj",
   "jn.",
   "Ptratf",
   "rnT2",
   "!r",
   "m",
   "?",
   "to",
   "1S",
   "I",
   "r",
   "!.",
   "or",
   "itr.",
   "j",
   "vu.iitbii,",
   "nupH",
   "iXZlZ",
   "JrVgrth",
   "Xtv"
  ],
  "page_seq_num": 195,
  "page_url": "https:\/\/chroniclingamerica.loc.gov\/data\/batches\/khi_jennison_ver01\/data\/sn82014635\/00280760511\/1895042701\/0195.jp2",
  "place_of_publication": "Wichita, Kan.",
  "pub_date": "1895-04-27",
  "publisher": "M.M. Murdock & R.P. Murdock",
  "score": 0.909850001335144,
  "url": "https:\/\/news-navigator.labs.loc.gov\/data\/khi_jennison_ver01\/data\/sn82014635\/00280760511\/1895042701\/0195\/010_0_90.jpg"
 },
 "id": 2
}