{
 "completions": [
  {
   "created_at": 1611675618,
   "id": 332001,
   "lead_time": 4.681,
   "result": [
    {
     "from_name": "choice",
     "id": "gx8Q_3_L0b",
     "to_name": "image",
     "type": "choices",
     "value": {
      "choices": [
       "human",
       "animal",
       "landscape"
      ]
     }
    }
   ]
  }
 ],
 "data": {
  "batch": "curiv_carlsbad_ver01",
  "box": [
   0.42350372728718894,
   0.44253501202224965,
   0.9674168375282806,
   0.7673790351065388
  ],
  "edition_seq_num": 1,
  "filepath": "curiv_carlsbad_ver01\/data\/sn85066387\/00175047505\/1899123101\/0731\/004_0_97.jpg",
  "geographic_coverage": [
   "California--San Francisco--San Francisco"
  ],
  "image": "https:\/\/chroniclingamerica.loc.gov\/iiif\/2\/curiv_carlsbad_ver01%2Fdata%2Fsn85066387%2F00175047505%2F1899123101%2F0731.jp2\/pct:42.35,44.26,54.4,32.49\/!500,500\/0\/default.jpg",
  "lccn": "sn85066387",
  "name": "The San Francisco call. [volume]",
  "ocr": [
   "Modder",
   "(Mud)",
   "River,",
   "the",
   "Scene",
   "of",
   "Lord",
   "Methuen's",
   "Battle",
   "November",
   "28.",
   "From",
   "the",
   "London",
   "Illustrated",
   "News",
   "The",
   "view",
   "Is",
   "from",
   "the",
   "north",
   "or",
   "Klmberley",
   "fide",
   "of",
   "the",
   "river.",
   "The",
   "battle",
   "wan",
   "on",
   "the",
   "south",
   "or",
   "far",
   "side.",
   "The",
   "Modder",
   "River,",
   "according",
   "to",
   "the",
   "notes",
   "of",
   "officer",
   "of",
   "Lord",
   "Methuen's",
   "command.",
   "I*",
   "Minethlng",
   "over",
   "forty",
   "jrmrdi",
   "wide,",
   "with",
   "steep,",
   "sandy",
   "bank*.",
   "The",
   "ground",
   "risen",
   "fn>m",
   "the",
   "river",
   "Ml",
   "and",
   "is",
   "MVOTti",
   "thirk",
   "mimosa",
   "scrub,",
   "affording",
   "excellent",
   "cover,",
   "of",
   "which",
   "the",
   "Boers",
   "availed",
   "themselves",
   "largely."
  ],
  "page_seq_num": 731,
  "page_url": "https:\/\/chroniclingamerica.loc.gov\/data\/batches\/curiv_carlsbad_ver01\/data\/sn85066387\/00175047505\/1899123101\/0731.jp2",
  "place_of_publication": "San Francisco [Calif.]",
  "pub_date": "1899-12-31",
  "publisher": "Charles M. Shortridge",
  "score": 0.9710361957550049,
  "url": "https:\/\/news-navigator.labs.loc.gov\/data\/curiv_carlsbad_ver01\/data\/sn85066387\/00175047505\/1899123101\/0731\/004_0_97.jpg"
 },
 "id": 332
}