{
 "completions": [
  {
   "created_at": 1611763915,
   "id": 538001,
   "lead_time": 3.514,
   "result": [
    {
     "from_name": "choice",
     "id": "goMnSgsbWd",
     "to_name": "image",
     "type": "choices",
     "value": {
      "choices": [
       "human"
      ]
     }
    }
   ]
  }
 ],
 "data": {
  "batch": "mthi_kestrel_ver02",
  "box": [
   0.14667845546784367,
   0.02719334937606655,
   0.9556518696300391,
   0.6645240132719177
  ],
  "edition_seq_num": 1,
  "filepath": "mthi_kestrel_ver02\/data\/sn83025294\/00295860327\/1901092101\/0197\/000_0_97.jpg",
  "geographic_coverage": [
   "Montana--Silver Bow--Butte"
  ],
  "image": "https:\/\/chroniclingamerica.loc.gov\/iiif\/2\/mthi_kestrel_ver02%2Fdata%2Fsn83025294%2F00295860327%2F1901092101%2F0197.jp2\/pct:14.66,2.72,80.9,63.74\/!500,500\/0\/default.jpg",
  "lccn": "sn83025294",
  "name": "The Butte inter mountain. [volume]",
  "ocr": [
   "ANNUAL",
   "MEETING",
   "HELD",
   "AT",
   "GREAT",
   "FALLS",
   "AND",
   "STEADY",
   "GROWTH",
   "DENOMINATION!",
   "OF",
   "MONTANA.",
   "OIF",
   "*3",
   "\\",
   "\u00cf",
   "'",
   "1",
   "^",
   "Y",
   "REVf",
   "^",
   "W.",
   "M",
   "-SETTER.",
   "ANACONDA",
   "henry",
   "r'copE",
   "PILL<?N",
   "meeting",
   "of",
   "association",
   "the",
   "First",
   "Bap-",
   "i",
   "September",
   "Baptists",
   "and",
   "will",
   "be",
   "j",
   "25",
   "churches,",
   "are",
   "American,",
   "and",
   "with",
   "are",
   "con",
   "have",
   "been",
   "twenty",
   "years.",
   "place",
   "in",
   "Hel",
   "is",
   "not",
   "regarded",
   "Baptists,",
   "i",
   "has",
   "grown",
   "one",
   "|",
   "of",
   "Zion,",
   "for",
   "j",
   "church",
   "in",
   "the",
   "|",
   "j",
   "new",
   "organiza-",
   "j",
   "struggles",
   "in",
   "their",
   "home",
   "and",
   "!",
   "After",
   "a",
   "few",
   "B.",
   "Allen",
   "was",
   "and",
   "labored",
   "for",
   "himself",
   "ai",
   "that",
   "place",
   "and",
   "wise",
   "leadership",
   "1",
   "spiritually,",
   "nu-",
   "i",
   "I",
   "to",
   "go",
   "J.",
   "F.",
   "McNamee",
   "and",
   "has",
   "a",
   "leader,",
   "so",
   "the",
   "prosper,",
   "and",
   "just",
   "are",
   "being",
   "organized",
   "and",
   "Stevens",
   "church",
   "have",
   "gone",
   "out",
   "three",
   "missions",
   "which",
   "are",
   "nearly",
   "ready",
   "to",
   "culminate",
   "Into",
   "churches,",
   "The",
   "church",
   "organized",
   "at",
   "Stevensville",
   "is",
   "numbered",
   "among",
   "the",
   "strongest",
   "church",
   "organizations",
   "in",
   "that",
   "part",
   "of",
   "the",
   "state.",
   "lt",
   "is",
   "free",
   "from",
   "debt,",
   "owing",
   "the",
   "most",
   "beautiful",
   "house",
   "of",
   "worship",
   "In",
   "that",
   "his",
   "toric",
   "old",
   "town,",
   "the",
   "place",
   "where",
   "the",
   "old",
   "It",
   "aval",
   "li",
   "(Catholic)",
   "mission",
   "was",
   "estab",
   "lished",
   "some",
   "50",
   "or",
   "60",
   "years",
   "ago.",
   "It",
   "was",
   "with",
   "this",
   "church",
   "that",
   "the",
   "gen",
   "eral",
   "association",
   "met",
   "last",
   "year,",
   "and",
   "in",
   "no",
   "place",
   "have",
   "they",
   "met",
   "a",
   "more",
   "warm",
   "hearted",
   "people",
   "or",
   "been",
   "more",
   "royally",
   "re",
   "ceived.",
   "Just",
   "about",
   "this",
   "time",
   "(1883)",
   "Baptist",
   "or",
   "gartizalions,",
   "like",
   "young",
   "colonies,",
   "began",
   "to",
   "spring",
   "up",
   "in",
   "various",
   "parts",
   "of",
   "the",
   "sit'ute,",
   "meeting",
   "in",
   "sehoolhouses,",
   "store",
   "rooms",
   "and",
   "such",
   "other",
   "places",
   "as",
   "they",
   "could",
   "secure",
   "for",
   "the",
   "holding",
   "of",
   "worship,",
   "But",
   "today",
   "they",
   "own",
   "their",
   "own",
   "churches,",
   "whose",
   "towers",
   "stand",
   "as",
   "monuments",
   "to",
   "all",
   "of",
   "the",
   "leading",
   "cities",
   "and",
   "towns",
   "and",
   "many",
   "of",
   "the",
   "smaller",
   "places,",
   "But",
   "the",
   "building",
   "of",
   "these",
   "houses",
   "of",
   "worship",
   "is",
   "only",
   "a",
   "small",
   "part",
   "of",
   "the",
   "work,",
   "done",
   "by",
   "these",
   "churches.",
   "They",
   "'have",
   "labored",
   "hard",
   "for",
   "the",
   "good",
   "mankind,",
   "socially,",
   "morally",
   "and",
   "spiritually.",
   "They",
   "have",
   "stood",
   "as",
   "a",
   "brave",
   "defense",
   "for",
   "tem",
   "perance",
   "and",
   "for",
   "the",
   "putting",
   "down",
   "of",
   "all",
   "kinds",
   "of",
   "vice,",
   "and",
   "for",
   "everything",
   "that",
   "would",
   "have",
   "a",
   "tendency",
   "to",
   "lead",
   "mankinl",
   "in",
   "humanity's",
   "scale.",
   "All",
   "of",
   "these",
   "churches",
   "deserve",
   "special",
   "mention",
   "of",
   "their",
   "work.",
   "The",
   "Swedish",
   "work",
   "in",
   "the",
   "state",
   "among",
   "their",
   "own",
   "people",
   "who",
   "have",
   "not",
   "suffi",
   "ciently",
   "acquired",
   "our",
   "language",
   "to",
   "be",
   "REV\u00ce",
   "ML.",
   "RKMIan",
   "BOZEMAN",
   "RE.",
   "Y",
   "\\",
   "T.",
   "L.",
   "LEWIS",
   "BOZEMAN",
   "m.",
   "\u2022",
   "3*",
   "r",
   "REW",
   "MILLER",
   "BELT",
   "BLv",
   "_",
   "Y^.",
   "W",
   "FV",
   "V^,",
   "RICKMAN",
   "STEVENSVILLE",
   "AND",
   "HAMILTON"
  ],
  "page_seq_num": 197,
  "page_url": "https:\/\/chroniclingamerica.loc.gov\/data\/batches\/mthi_kestrel_ver02\/data\/sn83025294\/00295860327\/1901092101\/0197.jp2",
  "place_of_publication": "Butte, Mont.",
  "pub_date": "1901-09-21",
  "publisher": "Inter Mountain Pub. Co.",
  "score": 0.9727985262870789,
  "url": "https:\/\/news-navigator.labs.loc.gov\/data\/mthi_kestrel_ver02\/data\/sn83025294\/00295860327\/1901092101\/0197\/000_0_97.jpg"
 },
 "id": 538
}