{
 "completions": [
  {
   "created_at": 1611768319,
   "id": 586001,
   "lead_time": 1.956,
   "result": [
    {
     "from_name": "choice",
     "id": "VI6pgq38Zr",
     "to_name": "image",
     "type": "choices",
     "value": {
      "choices": [
       "human"
      ]
     }
    }
   ]
  }
 ],
 "data": {
  "batch": "khi_higuchi_ver01",
  "box": [
   0.3055904349721674,
   0.05623959085848129,
   0.5647939447620138,
   0.36997152352128515
  ],
  "edition_seq_num": 1,
  "filepath": "khi_higuchi_ver01\/data\/sn82016014\/00295871106\/1902122001\/0793\/006_0_94.jpg",
  "geographic_coverage": [
   "Kansas--Shawnee--Topeka"
  ],
  "image": "https:\/\/chroniclingamerica.loc.gov\/iiif\/2\/khi_higuchi_ver01%2Fdata%2Fsn82016014%2F00295871106%2F1902122001%2F0793.jp2\/pct:30.55,5.63,25.93,31.38\/!500,500\/0\/default.jpg",
  "lccn": "sn82016014",
  "name": "The Topeka state journal. [volume]",
  "ocr": [
   "I",
   "J",
   "?Vsir.",
   "s",
   "'",
   "'",
   ".r-",
   "H",
   "k",
   "t.",
   "t&",
   "1",
   "-",
   "-",
   "I",
   "H",
   "J?&Z.tfSj",
   "I",
   "t",
   "j",
   "i",
   ")!!",
   "i",
   "\"rg",
   "'",
   ".",
   ".",
   ";",
   "I",
   "r",
   "vw",
   ":2-",
   ";",
   "v",
   "i",
   "1",
   "l",
   "s",
   "i",
   "v",
   "s",
   "-",
   "M",
   "11",
   "'",
   "'",
   "'St-:,",
   ".",
   "sj",
   "fl",
   ";",
   "J",
   "r",
   "-",
   "-",
   "-",
   "I",
   "\"",
   "Oys.",
   "J",
   "$",
   "--",
   "J",
   "...jTZc,r-.s",
   "S",
   "V-\"",
   "!",
   "..J",
   "'.;;.i.CF'\".\"f",
   "?i",
   "&",
   "1",
   "sfe-iv",
   "t.",
   "a",
   "r",
   "i",
   "i",
   "I",
   "i",
   "V",
   "1",
   "faaaJBaBSwsr",
   "One",
   "of",
   "the",
   "most",
   "notable",
   "figures",
   "of",
   "the",
   "United",
   "States",
   "Senate",
   "is",
   "Rev.",
   "Dr.",
   "Mil-"
  ],
  "page_seq_num": 793,
  "page_url": "https:\/\/chroniclingamerica.loc.gov\/data\/batches\/khi_higuchi_ver01\/data\/sn82016014\/00295871106\/1902122001\/0793.jp2",
  "place_of_publication": "Topeka, Kan.",
  "pub_date": "1902-12-20",
  "publisher": "F.P. MacLennan",
  "score": 0.9444373846054077,
  "url": "https:\/\/news-navigator.labs.loc.gov\/data\/khi_higuchi_ver01\/data\/sn82016014\/00295871106\/1902122001\/0793\/006_0_94.jpg"
 },
 "id": 586
}