{
 "completions": [
  {
   "created_at": 1611763781,
   "id": 77001,
   "lead_time": 4.009,
   "result": [
    {
     "from_name": "choice",
     "id": "bqje99cBGL",
     "to_name": "image",
     "type": "choices",
     "value": {
      "choices": [
       "human-structure"
      ]
     }
    }
   ]
  }
 ],
 "data": {
  "batch": "nbu_bryan_ver01",
  "box": [
   0.07205677508514455,
   0.051369594662102926,
   0.8964090204476913,
   0.4024815994783072
  ],
  "edition_seq_num": 1,
  "filepath": "nbu_bryan_ver01\/data\/sn99066033\/00237280477\/1896070401\/1907\/000_0_99.jpg",
  "geographic_coverage": [
   "Nebraska--Lancaster--Lincoln"
  ],
  "image": "https:\/\/chroniclingamerica.loc.gov\/iiif\/2\/nbu_bryan_ver01%2Fdata%2Fsn99066033%2F00237280477%2F1896070401%2F1907.jp2\/pct:7.2,5.14,82.44,35.12\/!500,500\/0\/default.jpg",
  "lccn": "sn99066033",
  "name": "The courier.",
  "ocr": [
   "c-",
   "2338",
   "&!",
   "s",
   "\"-",
   ".",
   "S,",
   "gr.",
   ":",
   "--",
   ".nt",
   "v-",
   "J5v",
   "ls",
   "ii",
   "r-ui",
   "i",
   "winji.iRti'-Hj",
   "i",
   "r",
   ".ra.",
   "j-jw",
   ".",
   "-",
   "-.",
   ".",
   "-",
   "-.",
   ":ttiTKaRh?w-y.-;",
   ",",
   ".",
   ".",
   ",(",
   "W",
   "ii",
   "1-i",
   "i",
   "J",
   "-",
   "xc",
   "Jfc.",
   "-",
   "vjifl)",
   ".bng.iv-.",
   "S",
   "wi'",
   "tJSStiSfeieS,",
   "L",
   "'",
   ".",
   "-",
   "-t'JKK2i",
   "jT",
   "t",
   "-\"\"!",
   "\"'",
   "!",
   "t",
   "4",
   "'f",
   "-",
   ",",
   "..",
   "-.j.",
   ",.",
   ".",
   ",jfc",
   "j",
   "saatii",
   "'",
   "---wiwswa",
   "\"",
   "-",
   ".\"r",
   "-i",
   "T-",
   "A.",
   ".",
   "-",
   "-",
   "-",
   "T",
   "u",
   "-.",
   "\"i.",
   "i",
   "V",
   "\"",
   "\"",
   "....",
   "-",
   ".",
   ",",
   "'.-nT,",
   "W?",
   "--\"",
   "-",
   "Jr,\"-''",
   ".",
   "WV-V",
   "31",
   "J..",
   "\"'?l",
   "r-",
   "-",
   "-",
   "fT",
   "Z'tftXjg&j&Si",
   "IKBm&xa&i&BSJaLJ&kfaWtti",
   "t",
   "'",
   "-",
   "tPkjiaKJMKrfRUI'",
   "3l.UFS3af",
   "rf?",
   "VBV-",
   "Ti",
   "M",
   "Trf",
   "etr",
   "i",
   "wv?mwiaias7",
   "'Arv.aHCjeaM'aiHWkM-m",
   "KSItt",
   "iv:",
   "a",
   "ryri",
   ".",
   "i",
   "WP",
   "ara98R",
   "SHp",
   "IBIIHEBUV.'Wl",
   "rasr-",
   "i.",
   "Ql",
   "mmmt",
   "K",
   "yWgca,",
   "f",
   ",,,,",
   "&'.",
   "s--2",
   "C",
   "I",
   ".",
   "-",
   "\".",
   "L-k",
   "8\"",
   "ft",
   "4M'",
   "-",
   ".",
   "EawflfiaVaav",
   "\"Mm",
   ".tBsllllllHsllHsiawLwW",
   ".",
   ",-",
   ":",
   ":",
   "-?.",
   "-",
   "&fK",
   "vrys--.",
   "r3Hl",
   "-K",
   "-",
   "&",
   "RE3",
   "i.wBs'rai",
   "ifflliiiaBiMHsaffilMI",
   "'\"",
   "\"-",
   "--",
   "BURLINGTON",
   "BBA6H"
  ],
  "page_seq_num": 1907,
  "page_url": "https:\/\/chroniclingamerica.loc.gov\/data\/batches\/nbu_bryan_ver01\/data\/sn99066033\/00237280477\/1896070401\/1907.jp2",
  "place_of_publication": "Lincoln, Neb.",
  "pub_date": "1896-07-04",
  "publisher": "Courier Pub. Co.",
  "score": 0.9977700710296631,
  "url": "https:\/\/news-navigator.labs.loc.gov\/data\/nbu_bryan_ver01\/data\/sn99066033\/00237280477\/1896070401\/1907\/000_0_99.jpg"
 },
 "id": 77
}